CHANGELOG.md
LICENSE
MANIFEST.in
README.md
VERSION
setup.cfg
setup.py
git_workspace/__init__.py
git_workspace/cli.py
git_workspace.egg-info/PKG-INFO
git_workspace.egg-info/SOURCES.txt
git_workspace.egg-info/dependency_links.txt
git_workspace.egg-info/entry_points.txt
git_workspace.egg-info/requires.txt
git_workspace.egg-info/top_level.txt
git_workspace/configuration/__init__.py
git_workspace/configuration/workspace.py
git_workspace/directory_operations/__init__.py
git_workspace/directory_operations/cleanup.py
git_workspace/git/__init__.py
git_workspace/git/operations.py
git_workspace/integrations/__init__.py
git_workspace/integrations/gitlab.py